LICENSE.text
MANIFEST.in
README.md
load_tester.py
setup.py
devox_load_tester.egg-info/PKG-INFO
devox_load_tester.egg-info/SOURCES.txt
devox_load_tester.egg-info/dependency_links.txt
devox_load_tester.egg-info/top_level.txt